{
    "channels": [
        {
            "name": "Red",
            "type": "Analog_8",
            "normalized": true,
            "defaultValue": 0
        },
        {
            "name": "Green",
            "type": "Analog_8",
            "normalized": true,
            "defaultValue": 0
        },
        {
            "name": "Blue",
            "type": "Analog_8",
            "normalized": true,
            "defaultValue": 0
        },
        {
            "name": "Dimmer",
            "type": "Analog_8",
            "normalized": true,
            "defaultValue": 0
        },
        {
            "name": "Effects",
            "type": "Ranges",
            "ranges": [
                {
                    "name": "NoFunction",
                    "first": 0,
                    "last": 0,
                    "discrete": true
                },
                {
                    "name": "Sound Control",
                    "first": 1,
                    "last": 5,
                    "discrete": true
                },
                {
                    "name": "ShutterStrobe",
                    "first": 11,
                    "last": 255
                }
            ]
        }
    ],
    "note": "Color Changer (imported from open-fixture-library)"
}